{
  "id": "e7abeb06-4faa-4f51-9c9b-10d144b94bbc",
  "prevId": "00000000-0000-0000-0000-000000000000",
  "version": "7",
  "dialect": "postgresql",
  "tables": {
    "public.books": {
      "name": "books",
      "schema": "",
      "columns": {
        "id": {
          "name": "id",
          "type": "serial",
          "primaryKey": true,
          "notNull": true
        },
        "slug": {
          "name": "slug",
          "type": "varchar(64)",
          "primaryKey": false,
          "notNull": true
        },
        "name": {
          "name": "name",
          "type": "text",
          "primaryKey": false,
          "notNull": true
        },
        "country": {
          "name": "country",
          "type": "varchar(3)",
          "primaryKey": false,
          "notNull": false
        },
        "tier": {
          "name": "tier",
          "type": "source_tier",
          "typeSchema": "public",
          "primaryKey": false,
          "notNull": true,
          "default": "'medium'"
        },
        "is_sharp": {
          "name": "is_sharp",
          "type": "boolean",
          "primaryKey": false,
          "notNull": true,
          "default": false
        },
        "rate_limit_rpm": {
          "name": "rate_limit_rpm",
          "type": "integer",
          "primaryKey": false,
          "notNull": true,
          "default": 60
        },
        "enabled": {
          "name": "enabled",
          "type": "boolean",
          "primaryKey": false,
          "notNull": true,
          "default": true
        },
        "config": {
          "name": "config",
          "type": "jsonb",
          "primaryKey": false,
          "notNull": true,
          "default": "'{}'::jsonb"
        },
        "created_at": {
          "name": "created_at",
          "type": "timestamp with time zone",
          "primaryKey": false,
          "notNull": true,
          "default": "now()"
        }
      },
      "indexes": {},
      "foreignKeys": {},
      "compositePrimaryKeys": {},
      "uniqueConstraints": {
        "books_slug_unique": {
          "name": "books_slug_unique",
          "nullsNotDistinct": false,
          "columns": [
            "slug"
          ]
        }
      },
      "policies": {},
      "checkConstraints": {},
      "isRLSEnabled": false
    },
    "public.competitions": {
      "name": "competitions",
      "schema": "",
      "columns": {
        "id": {
          "name": "id",
          "type": "serial",
          "primaryKey": true,
          "notNull": true
        },
        "sport_id": {
          "name": "sport_id",
          "type": "integer",
          "primaryKey": false,
          "notNull": true
        },
        "slug": {
          "name": "slug",
          "type": "varchar(128)",
          "primaryKey": false,
          "notNull": true
        },
        "name": {
          "name": "name",
          "type": "text",
          "primaryKey": false,
          "notNull": true
        },
        "country": {
          "name": "country",
          "type": "varchar(3)",
          "primaryKey": false,
          "notNull": false
        },
        "external_ids": {
          "name": "external_ids",
          "type": "jsonb",
          "primaryKey": false,
          "notNull": true,
          "default": "'{}'::jsonb"
        },
        "created_at": {
          "name": "created_at",
          "type": "timestamp with time zone",
          "primaryKey": false,
          "notNull": true,
          "default": "now()"
        }
      },
      "indexes": {
        "uniq_competition_sport_slug": {
          "name": "uniq_competition_sport_slug",
          "columns": [
            {
              "expression": "sport_id",
              "isExpression": false,
              "asc": true,
              "nulls": "last"
            },
            {
              "expression": "slug",
              "isExpression": false,
              "asc": true,
              "nulls": "last"
            }
          ],
          "isUnique": true,
          "concurrently": false,
          "method": "btree",
          "with": {}
        }
      },
      "foreignKeys": {
        "competitions_sport_id_sports_id_fk": {
          "name": "competitions_sport_id_sports_id_fk",
          "tableFrom": "competitions",
          "tableTo": "sports",
          "columnsFrom": [
            "sport_id"
          ],
          "columnsTo": [
            "id"
          ],
          "onDelete": "cascade",
          "onUpdate": "no action"
        }
      },
      "compositePrimaryKeys": {},
      "uniqueConstraints": {},
      "policies": {},
      "checkConstraints": {},
      "isRLSEnabled": false
    },
    "public.events": {
      "name": "events",
      "schema": "",
      "columns": {
        "id": {
          "name": "id",
          "type": "serial",
          "primaryKey": true,
          "notNull": true
        },
        "competition_id": {
          "name": "competition_id",
          "type": "integer",
          "primaryKey": false,
          "notNull": true
        },
        "home_team_id": {
          "name": "home_team_id",
          "type": "integer",
          "primaryKey": false,
          "notNull": true
        },
        "away_team_id": {
          "name": "away_team_id",
          "type": "integer",
          "primaryKey": false,
          "notNull": true
        },
        "kickoff_utc": {
          "name": "kickoff_utc",
          "type": "timestamp with time zone",
          "primaryKey": false,
          "notNull": true
        },
        "status": {
          "name": "status",
          "type": "event_status",
          "typeSchema": "public",
          "primaryKey": false,
          "notNull": true,
          "default": "'scheduled'"
        },
        "external_ids": {
          "name": "external_ids",
          "type": "jsonb",
          "primaryKey": false,
          "notNull": true,
          "default": "'{}'::jsonb"
        },
        "created_at": {
          "name": "created_at",
          "type": "timestamp with time zone",
          "primaryKey": false,
          "notNull": true,
          "default": "now()"
        }
      },
      "indexes": {
        "idx_events_kickoff": {
          "name": "idx_events_kickoff",
          "columns": [
            {
              "expression": "kickoff_utc",
              "isExpression": false,
              "asc": true,
              "nulls": "last"
            }
          ],
          "isUnique": false,
          "concurrently": false,
          "method": "btree",
          "with": {}
        },
        "idx_events_competition_kickoff": {
          "name": "idx_events_competition_kickoff",
          "columns": [
            {
              "expression": "competition_id",
              "isExpression": false,
              "asc": true,
              "nulls": "last"
            },
            {
              "expression": "kickoff_utc",
              "isExpression": false,
              "asc": true,
              "nulls": "last"
            }
          ],
          "isUnique": false,
          "concurrently": false,
          "method": "btree",
          "with": {}
        },
        "uniq_event_natural": {
          "name": "uniq_event_natural",
          "columns": [
            {
              "expression": "competition_id",
              "isExpression": false,
              "asc": true,
              "nulls": "last"
            },
            {
              "expression": "home_team_id",
              "isExpression": false,
              "asc": true,
              "nulls": "last"
            },
            {
              "expression": "away_team_id",
              "isExpression": false,
              "asc": true,
              "nulls": "last"
            },
            {
              "expression": "kickoff_utc",
              "isExpression": false,
              "asc": true,
              "nulls": "last"
            }
          ],
          "isUnique": true,
          "concurrently": false,
          "method": "btree",
          "with": {}
        }
      },
      "foreignKeys": {
        "events_competition_id_competitions_id_fk": {
          "name": "events_competition_id_competitions_id_fk",
          "tableFrom": "events",
          "tableTo": "competitions",
          "columnsFrom": [
            "competition_id"
          ],
          "columnsTo": [
            "id"
          ],
          "onDelete": "cascade",
          "onUpdate": "no action"
        },
        "events_home_team_id_teams_id_fk": {
          "name": "events_home_team_id_teams_id_fk",
          "tableFrom": "events",
          "tableTo": "teams",
          "columnsFrom": [
            "home_team_id"
          ],
          "columnsTo": [
            "id"
          ],
          "onDelete": "no action",
          "onUpdate": "no action"
        },
        "events_away_team_id_teams_id_fk": {
          "name": "events_away_team_id_teams_id_fk",
          "tableFrom": "events",
          "tableTo": "teams",
          "columnsFrom": [
            "away_team_id"
          ],
          "columnsTo": [
            "id"
          ],
          "onDelete": "no action",
          "onUpdate": "no action"
        }
      },
      "compositePrimaryKeys": {},
      "uniqueConstraints": {},
      "policies": {},
      "checkConstraints": {},
      "isRLSEnabled": false
    },
    "public.ingestion_runs": {
      "name": "ingestion_runs",
      "schema": "",
      "columns": {
        "id": {
          "name": "id",
          "type": "serial",
          "primaryKey": true,
          "notNull": true
        },
        "book_id": {
          "name": "book_id",
          "type": "integer",
          "primaryKey": false,
          "notNull": true
        },
        "started_at": {
          "name": "started_at",
          "type": "timestamp with time zone",
          "primaryKey": false,
          "notNull": true,
          "default": "now()"
        },
        "finished_at": {
          "name": "finished_at",
          "type": "timestamp with time zone",
          "primaryKey": false,
          "notNull": false
        },
        "items_fetched": {
          "name": "items_fetched",
          "type": "integer",
          "primaryKey": false,
          "notNull": true,
          "default": 0
        },
        "items_inserted": {
          "name": "items_inserted",
          "type": "integer",
          "primaryKey": false,
          "notNull": true,
          "default": 0
        },
        "errors_count": {
          "name": "errors_count",
          "type": "integer",
          "primaryKey": false,
          "notNull": true,
          "default": 0
        },
        "status": {
          "name": "status",
          "type": "ingestion_status",
          "typeSchema": "public",
          "primaryKey": false,
          "notNull": true,
          "default": "'running'"
        },
        "note": {
          "name": "note",
          "type": "text",
          "primaryKey": false,
          "notNull": false
        }
      },
      "indexes": {
        "idx_ingestion_book_started": {
          "name": "idx_ingestion_book_started",
          "columns": [
            {
              "expression": "book_id",
              "isExpression": false,
              "asc": true,
              "nulls": "last"
            },
            {
              "expression": "started_at",
              "isExpression": false,
              "asc": true,
              "nulls": "last"
            }
          ],
          "isUnique": false,
          "concurrently": false,
          "method": "btree",
          "with": {}
        }
      },
      "foreignKeys": {
        "ingestion_runs_book_id_books_id_fk": {
          "name": "ingestion_runs_book_id_books_id_fk",
          "tableFrom": "ingestion_runs",
          "tableTo": "books",
          "columnsFrom": [
            "book_id"
          ],
          "columnsTo": [
            "id"
          ],
          "onDelete": "cascade",
          "onUpdate": "no action"
        }
      },
      "compositePrimaryKeys": {},
      "uniqueConstraints": {},
      "policies": {},
      "checkConstraints": {},
      "isRLSEnabled": false
    },
    "public.mapping_review": {
      "name": "mapping_review",
      "schema": "",
      "columns": {
        "id": {
          "name": "id",
          "type": "serial",
          "primaryKey": true,
          "notNull": true
        },
        "entity_type": {
          "name": "entity_type",
          "type": "varchar(32)",
          "primaryKey": false,
          "notNull": true
        },
        "source_book_id": {
          "name": "source_book_id",
          "type": "integer",
          "primaryKey": false,
          "notNull": false
        },
        "source_value": {
          "name": "source_value",
          "type": "text",
          "primaryKey": false,
          "notNull": true
        },
        "candidates": {
          "name": "candidates",
          "type": "jsonb",
          "primaryKey": false,
          "notNull": true,
          "default": "'[]'::jsonb"
        },
        "status": {
          "name": "status",
          "type": "mapping_status",
          "typeSchema": "public",
          "primaryKey": false,
          "notNull": true,
          "default": "'pending'"
        },
        "resolved_to_id": {
          "name": "resolved_to_id",
          "type": "integer",
          "primaryKey": false,
          "notNull": false
        },
        "resolved_at": {
          "name": "resolved_at",
          "type": "timestamp with time zone",
          "primaryKey": false,
          "notNull": false
        },
        "created_at": {
          "name": "created_at",
          "type": "timestamp with time zone",
          "primaryKey": false,
          "notNull": true,
          "default": "now()"
        }
      },
      "indexes": {},
      "foreignKeys": {
        "mapping_review_source_book_id_books_id_fk": {
          "name": "mapping_review_source_book_id_books_id_fk",
          "tableFrom": "mapping_review",
          "tableTo": "books",
          "columnsFrom": [
            "source_book_id"
          ],
          "columnsTo": [
            "id"
          ],
          "onDelete": "no action",
          "onUpdate": "no action"
        }
      },
      "compositePrimaryKeys": {},
      "uniqueConstraints": {},
      "policies": {},
      "checkConstraints": {},
      "isRLSEnabled": false
    },
    "public.markets": {
      "name": "markets",
      "schema": "",
      "columns": {
        "id": {
          "name": "id",
          "type": "serial",
          "primaryKey": true,
          "notNull": true
        },
        "slug": {
          "name": "slug",
          "type": "varchar(64)",
          "primaryKey": false,
          "notNull": true
        },
        "name": {
          "name": "name",
          "type": "text",
          "primaryKey": false,
          "notNull": true
        },
        "type": {
          "name": "type",
          "type": "varchar(32)",
          "primaryKey": false,
          "notNull": true
        },
        "config": {
          "name": "config",
          "type": "jsonb",
          "primaryKey": false,
          "notNull": true,
          "default": "'{}'::jsonb"
        }
      },
      "indexes": {},
      "foreignKeys": {},
      "compositePrimaryKeys": {},
      "uniqueConstraints": {
        "markets_slug_unique": {
          "name": "markets_slug_unique",
          "nullsNotDistinct": false,
          "columns": [
            "slug"
          ]
        }
      },
      "policies": {},
      "checkConstraints": {},
      "isRLSEnabled": false
    },
    "public.notifications": {
      "name": "notifications",
      "schema": "",
      "columns": {
        "id": {
          "name": "id",
          "type": "serial",
          "primaryKey": true,
          "notNull": true
        },
        "signal_id": {
          "name": "signal_id",
          "type": "integer",
          "primaryKey": false,
          "notNull": true
        },
        "rule_id": {
          "name": "rule_id",
          "type": "integer",
          "primaryKey": false,
          "notNull": false
        },
        "channel": {
          "name": "channel",
          "type": "varchar(32)",
          "primaryKey": false,
          "notNull": true
        },
        "status": {
          "name": "status",
          "type": "varchar(32)",
          "primaryKey": false,
          "notNull": true
        },
        "sent_at": {
          "name": "sent_at",
          "type": "timestamp with time zone",
          "primaryKey": false,
          "notNull": false
        },
        "error": {
          "name": "error",
          "type": "text",
          "primaryKey": false,
          "notNull": false
        },
        "created_at": {
          "name": "created_at",
          "type": "timestamp with time zone",
          "primaryKey": false,
          "notNull": true,
          "default": "now()"
        }
      },
      "indexes": {
        "idx_notifications_signal": {
          "name": "idx_notifications_signal",
          "columns": [
            {
              "expression": "signal_id",
              "isExpression": false,
              "asc": true,
              "nulls": "last"
            }
          ],
          "isUnique": false,
          "concurrently": false,
          "method": "btree",
          "with": {}
        }
      },
      "foreignKeys": {
        "notifications_signal_id_signals_id_fk": {
          "name": "notifications_signal_id_signals_id_fk",
          "tableFrom": "notifications",
          "tableTo": "signals",
          "columnsFrom": [
            "signal_id"
          ],
          "columnsTo": [
            "id"
          ],
          "onDelete": "cascade",
          "onUpdate": "no action"
        },
        "notifications_rule_id_signal_rules_id_fk": {
          "name": "notifications_rule_id_signal_rules_id_fk",
          "tableFrom": "notifications",
          "tableTo": "signal_rules",
          "columnsFrom": [
            "rule_id"
          ],
          "columnsTo": [
            "id"
          ],
          "onDelete": "set null",
          "onUpdate": "no action"
        }
      },
      "compositePrimaryKeys": {},
      "uniqueConstraints": {},
      "policies": {},
      "checkConstraints": {},
      "isRLSEnabled": false
    },
    "public.odds_snapshots": {
      "name": "odds_snapshots",
      "schema": "",
      "columns": {
        "id": {
          "name": "id",
          "type": "bigint",
          "primaryKey": false,
          "notNull": true,
          "identity": {
            "type": "always",
            "name": "odds_snapshots_id_seq",
            "schema": "public",
            "increment": "1",
            "startWith": "1",
            "minValue": "1",
            "maxValue": "9223372036854775807",
            "cache": "1",
            "cycle": false
          }
        },
        "taken_at": {
          "name": "taken_at",
          "type": "timestamp with time zone",
          "primaryKey": false,
          "notNull": true
        },
        "event_id": {
          "name": "event_id",
          "type": "integer",
          "primaryKey": false,
          "notNull": true
        },
        "market_id": {
          "name": "market_id",
          "type": "integer",
          "primaryKey": false,
          "notNull": true
        },
        "selection_id": {
          "name": "selection_id",
          "type": "integer",
          "primaryKey": false,
          "notNull": true
        },
        "book_id": {
          "name": "book_id",
          "type": "integer",
          "primaryKey": false,
          "notNull": true
        },
        "odd": {
          "name": "odd",
          "type": "double precision",
          "primaryKey": false,
          "notNull": true
        },
        "is_in_play": {
          "name": "is_in_play",
          "type": "boolean",
          "primaryKey": false,
          "notNull": true,
          "default": false
        },
        "raw": {
          "name": "raw",
          "type": "jsonb",
          "primaryKey": false,
          "notNull": false
        }
      },
      "indexes": {
        "idx_odds_lookup": {
          "name": "idx_odds_lookup",
          "columns": [
            {
              "expression": "event_id",
              "isExpression": false,
              "asc": true,
              "nulls": "last"
            },
            {
              "expression": "market_id",
              "isExpression": false,
              "asc": true,
              "nulls": "last"
            },
            {
              "expression": "selection_id",
              "isExpression": false,
              "asc": true,
              "nulls": "last"
            },
            {
              "expression": "book_id",
              "isExpression": false,
              "asc": true,
              "nulls": "last"
            },
            {
              "expression": "taken_at",
              "isExpression": false,
              "asc": true,
              "nulls": "last"
            }
          ],
          "isUnique": false,
          "concurrently": false,
          "method": "btree",
          "with": {}
        },
        "idx_odds_event_time": {
          "name": "idx_odds_event_time",
          "columns": [
            {
              "expression": "event_id",
              "isExpression": false,
              "asc": true,
              "nulls": "last"
            },
            {
              "expression": "taken_at",
              "isExpression": false,
              "asc": true,
              "nulls": "last"
            }
          ],
          "isUnique": false,
          "concurrently": false,
          "method": "btree",
          "with": {}
        }
      },
      "foreignKeys": {
        "odds_snapshots_event_id_events_id_fk": {
          "name": "odds_snapshots_event_id_events_id_fk",
          "tableFrom": "odds_snapshots",
          "tableTo": "events",
          "columnsFrom": [
            "event_id"
          ],
          "columnsTo": [
            "id"
          ],
          "onDelete": "cascade",
          "onUpdate": "no action"
        },
        "odds_snapshots_market_id_markets_id_fk": {
          "name": "odds_snapshots_market_id_markets_id_fk",
          "tableFrom": "odds_snapshots",
          "tableTo": "markets",
          "columnsFrom": [
            "market_id"
          ],
          "columnsTo": [
            "id"
          ],
          "onDelete": "no action",
          "onUpdate": "no action"
        },
        "odds_snapshots_selection_id_selections_id_fk": {
          "name": "odds_snapshots_selection_id_selections_id_fk",
          "tableFrom": "odds_snapshots",
          "tableTo": "selections",
          "columnsFrom": [
            "selection_id"
          ],
          "columnsTo": [
            "id"
          ],
          "onDelete": "no action",
          "onUpdate": "no action"
        },
        "odds_snapshots_book_id_books_id_fk": {
          "name": "odds_snapshots_book_id_books_id_fk",
          "tableFrom": "odds_snapshots",
          "tableTo": "books",
          "columnsFrom": [
            "book_id"
          ],
          "columnsTo": [
            "id"
          ],
          "onDelete": "no action",
          "onUpdate": "no action"
        }
      },
      "compositePrimaryKeys": {
        "odds_snapshots_id_taken_at_pk": {
          "name": "odds_snapshots_id_taken_at_pk",
          "columns": [
            "id",
            "taken_at"
          ]
        }
      },
      "uniqueConstraints": {},
      "policies": {},
      "checkConstraints": {},
      "isRLSEnabled": false
    },
    "public.selections": {
      "name": "selections",
      "schema": "",
      "columns": {
        "id": {
          "name": "id",
          "type": "serial",
          "primaryKey": true,
          "notNull": true
        },
        "market_id": {
          "name": "market_id",
          "type": "integer",
          "primaryKey": false,
          "notNull": true
        },
        "slug": {
          "name": "slug",
          "type": "varchar(64)",
          "primaryKey": false,
          "notNull": true
        },
        "name": {
          "name": "name",
          "type": "text",
          "primaryKey": false,
          "notNull": true
        }
      },
      "indexes": {
        "uniq_selection_market_slug": {
          "name": "uniq_selection_market_slug",
          "columns": [
            {
              "expression": "market_id",
              "isExpression": false,
              "asc": true,
              "nulls": "last"
            },
            {
              "expression": "slug",
              "isExpression": false,
              "asc": true,
              "nulls": "last"
            }
          ],
          "isUnique": true,
          "concurrently": false,
          "method": "btree",
          "with": {}
        }
      },
      "foreignKeys": {
        "selections_market_id_markets_id_fk": {
          "name": "selections_market_id_markets_id_fk",
          "tableFrom": "selections",
          "tableTo": "markets",
          "columnsFrom": [
            "market_id"
          ],
          "columnsTo": [
            "id"
          ],
          "onDelete": "cascade",
          "onUpdate": "no action"
        }
      },
      "compositePrimaryKeys": {},
      "uniqueConstraints": {},
      "policies": {},
      "checkConstraints": {},
      "isRLSEnabled": false
    },
    "public.signal_rules": {
      "name": "signal_rules",
      "schema": "",
      "columns": {
        "id": {
          "name": "id",
          "type": "serial",
          "primaryKey": true,
          "notNull": true
        },
        "user_id": {
          "name": "user_id",
          "type": "integer",
          "primaryKey": false,
          "notNull": true
        },
        "name": {
          "name": "name",
          "type": "text",
          "primaryKey": false,
          "notNull": true
        },
        "filter": {
          "name": "filter",
          "type": "jsonb",
          "primaryKey": false,
          "notNull": true,
          "default": "'{}'::jsonb"
        },
        "threshold_edge": {
          "name": "threshold_edge",
          "type": "double precision",
          "primaryKey": false,
          "notNull": true,
          "default": 0.03
        },
        "channels": {
          "name": "channels",
          "type": "jsonb",
          "primaryKey": false,
          "notNull": true,
          "default": "'[\"web\"]'::jsonb"
        },
        "enabled": {
          "name": "enabled",
          "type": "boolean",
          "primaryKey": false,
          "notNull": true,
          "default": true
        },
        "created_at": {
          "name": "created_at",
          "type": "timestamp with time zone",
          "primaryKey": false,
          "notNull": true,
          "default": "now()"
        }
      },
      "indexes": {},
      "foreignKeys": {
        "signal_rules_user_id_users_id_fk": {
          "name": "signal_rules_user_id_users_id_fk",
          "tableFrom": "signal_rules",
          "tableTo": "users",
          "columnsFrom": [
            "user_id"
          ],
          "columnsTo": [
            "id"
          ],
          "onDelete": "cascade",
          "onUpdate": "no action"
        }
      },
      "compositePrimaryKeys": {},
      "uniqueConstraints": {},
      "policies": {},
      "checkConstraints": {},
      "isRLSEnabled": false
    },
    "public.signals": {
      "name": "signals",
      "schema": "",
      "columns": {
        "id": {
          "name": "id",
          "type": "serial",
          "primaryKey": true,
          "notNull": true
        },
        "type": {
          "name": "type",
          "type": "signal_type",
          "typeSchema": "public",
          "primaryKey": false,
          "notNull": true
        },
        "event_id": {
          "name": "event_id",
          "type": "integer",
          "primaryKey": false,
          "notNull": true
        },
        "market_id": {
          "name": "market_id",
          "type": "integer",
          "primaryKey": false,
          "notNull": false
        },
        "selection_id": {
          "name": "selection_id",
          "type": "integer",
          "primaryKey": false,
          "notNull": false
        },
        "edge": {
          "name": "edge",
          "type": "double precision",
          "primaryKey": false,
          "notNull": true
        },
        "payload": {
          "name": "payload",
          "type": "jsonb",
          "primaryKey": false,
          "notNull": true
        },
        "status": {
          "name": "status",
          "type": "signal_status",
          "typeSchema": "public",
          "primaryKey": false,
          "notNull": true,
          "default": "'active'"
        },
        "created_at": {
          "name": "created_at",
          "type": "timestamp with time zone",
          "primaryKey": false,
          "notNull": true,
          "default": "now()"
        },
        "expires_at": {
          "name": "expires_at",
          "type": "timestamp with time zone",
          "primaryKey": false,
          "notNull": false
        }
      },
      "indexes": {
        "idx_signals_created": {
          "name": "idx_signals_created",
          "columns": [
            {
              "expression": "created_at",
              "isExpression": false,
              "asc": true,
              "nulls": "last"
            }
          ],
          "isUnique": false,
          "concurrently": false,
          "method": "btree",
          "with": {}
        },
        "idx_signals_type_status": {
          "name": "idx_signals_type_status",
          "columns": [
            {
              "expression": "type",
              "isExpression": false,
              "asc": true,
              "nulls": "last"
            },
            {
              "expression": "status",
              "isExpression": false,
              "asc": true,
              "nulls": "last"
            }
          ],
          "isUnique": false,
          "concurrently": false,
          "method": "btree",
          "with": {}
        },
        "idx_signals_event": {
          "name": "idx_signals_event",
          "columns": [
            {
              "expression": "event_id",
              "isExpression": false,
              "asc": true,
              "nulls": "last"
            }
          ],
          "isUnique": false,
          "concurrently": false,
          "method": "btree",
          "with": {}
        }
      },
      "foreignKeys": {
        "signals_event_id_events_id_fk": {
          "name": "signals_event_id_events_id_fk",
          "tableFrom": "signals",
          "tableTo": "events",
          "columnsFrom": [
            "event_id"
          ],
          "columnsTo": [
            "id"
          ],
          "onDelete": "cascade",
          "onUpdate": "no action"
        },
        "signals_market_id_markets_id_fk": {
          "name": "signals_market_id_markets_id_fk",
          "tableFrom": "signals",
          "tableTo": "markets",
          "columnsFrom": [
            "market_id"
          ],
          "columnsTo": [
            "id"
          ],
          "onDelete": "no action",
          "onUpdate": "no action"
        },
        "signals_selection_id_selections_id_fk": {
          "name": "signals_selection_id_selections_id_fk",
          "tableFrom": "signals",
          "tableTo": "selections",
          "columnsFrom": [
            "selection_id"
          ],
          "columnsTo": [
            "id"
          ],
          "onDelete": "no action",
          "onUpdate": "no action"
        }
      },
      "compositePrimaryKeys": {},
      "uniqueConstraints": {},
      "policies": {},
      "checkConstraints": {},
      "isRLSEnabled": false
    },
    "public.sports": {
      "name": "sports",
      "schema": "",
      "columns": {
        "id": {
          "name": "id",
          "type": "serial",
          "primaryKey": true,
          "notNull": true
        },
        "slug": {
          "name": "slug",
          "type": "varchar(64)",
          "primaryKey": false,
          "notNull": true
        },
        "name": {
          "name": "name",
          "type": "text",
          "primaryKey": false,
          "notNull": true
        },
        "created_at": {
          "name": "created_at",
          "type": "timestamp with time zone",
          "primaryKey": false,
          "notNull": true,
          "default": "now()"
        }
      },
      "indexes": {},
      "foreignKeys": {},
      "compositePrimaryKeys": {},
      "uniqueConstraints": {
        "sports_slug_unique": {
          "name": "sports_slug_unique",
          "nullsNotDistinct": false,
          "columns": [
            "slug"
          ]
        }
      },
      "policies": {},
      "checkConstraints": {},
      "isRLSEnabled": false
    },
    "public.team_aliases": {
      "name": "team_aliases",
      "schema": "",
      "columns": {
        "id": {
          "name": "id",
          "type": "serial",
          "primaryKey": true,
          "notNull": true
        },
        "team_id": {
          "name": "team_id",
          "type": "integer",
          "primaryKey": false,
          "notNull": true
        },
        "alias": {
          "name": "alias",
          "type": "text",
          "primaryKey": false,
          "notNull": true
        },
        "source_book_id": {
          "name": "source_book_id",
          "type": "integer",
          "primaryKey": false,
          "notNull": false
        },
        "confidence": {
          "name": "confidence",
          "type": "double precision",
          "primaryKey": false,
          "notNull": true,
          "default": 1
        },
        "verified": {
          "name": "verified",
          "type": "boolean",
          "primaryKey": false,
          "notNull": true,
          "default": false
        },
        "created_at": {
          "name": "created_at",
          "type": "timestamp with time zone",
          "primaryKey": false,
          "notNull": true,
          "default": "now()"
        }
      },
      "indexes": {
        "uniq_team_alias": {
          "name": "uniq_team_alias",
          "columns": [
            {
              "expression": "team_id",
              "isExpression": false,
              "asc": true,
              "nulls": "last"
            },
            {
              "expression": "alias",
              "isExpression": false,
              "asc": true,
              "nulls": "last"
            }
          ],
          "isUnique": true,
          "concurrently": false,
          "method": "btree",
          "with": {}
        },
        "idx_team_alias_trgm": {
          "name": "idx_team_alias_trgm",
          "columns": [
            {
              "expression": "alias",
              "isExpression": false,
              "asc": true,
              "nulls": "last"
            }
          ],
          "isUnique": false,
          "concurrently": false,
          "method": "btree",
          "with": {}
        }
      },
      "foreignKeys": {
        "team_aliases_team_id_teams_id_fk": {
          "name": "team_aliases_team_id_teams_id_fk",
          "tableFrom": "team_aliases",
          "tableTo": "teams",
          "columnsFrom": [
            "team_id"
          ],
          "columnsTo": [
            "id"
          ],
          "onDelete": "cascade",
          "onUpdate": "no action"
        }
      },
      "compositePrimaryKeys": {},
      "uniqueConstraints": {},
      "policies": {},
      "checkConstraints": {},
      "isRLSEnabled": false
    },
    "public.teams": {
      "name": "teams",
      "schema": "",
      "columns": {
        "id": {
          "name": "id",
          "type": "serial",
          "primaryKey": true,
          "notNull": true
        },
        "sport_id": {
          "name": "sport_id",
          "type": "integer",
          "primaryKey": false,
          "notNull": true
        },
        "name_canonical": {
          "name": "name_canonical",
          "type": "text",
          "primaryKey": false,
          "notNull": true
        },
        "country": {
          "name": "country",
          "type": "varchar(3)",
          "primaryKey": false,
          "notNull": false
        },
        "created_at": {
          "name": "created_at",
          "type": "timestamp with time zone",
          "primaryKey": false,
          "notNull": true,
          "default": "now()"
        }
      },
      "indexes": {
        "idx_teams_sport_name": {
          "name": "idx_teams_sport_name",
          "columns": [
            {
              "expression": "sport_id",
              "isExpression": false,
              "asc": true,
              "nulls": "last"
            },
            {
              "expression": "name_canonical",
              "isExpression": false,
              "asc": true,
              "nulls": "last"
            }
          ],
          "isUnique": false,
          "concurrently": false,
          "method": "btree",
          "with": {}
        }
      },
      "foreignKeys": {
        "teams_sport_id_sports_id_fk": {
          "name": "teams_sport_id_sports_id_fk",
          "tableFrom": "teams",
          "tableTo": "sports",
          "columnsFrom": [
            "sport_id"
          ],
          "columnsTo": [
            "id"
          ],
          "onDelete": "cascade",
          "onUpdate": "no action"
        }
      },
      "compositePrimaryKeys": {},
      "uniqueConstraints": {},
      "policies": {},
      "checkConstraints": {},
      "isRLSEnabled": false
    },
    "public.users": {
      "name": "users",
      "schema": "",
      "columns": {
        "id": {
          "name": "id",
          "type": "serial",
          "primaryKey": true,
          "notNull": true
        },
        "email": {
          "name": "email",
          "type": "varchar(255)",
          "primaryKey": false,
          "notNull": true
        },
        "password_hash": {
          "name": "password_hash",
          "type": "text",
          "primaryKey": false,
          "notNull": true
        },
        "role": {
          "name": "role",
          "type": "user_role",
          "typeSchema": "public",
          "primaryKey": false,
          "notNull": true,
          "default": "'admin'"
        },
        "telegram_chat_id": {
          "name": "telegram_chat_id",
          "type": "varchar(64)",
          "primaryKey": false,
          "notNull": false
        },
        "created_at": {
          "name": "created_at",
          "type": "timestamp with time zone",
          "primaryKey": false,
          "notNull": true,
          "default": "now()"
        }
      },
      "indexes": {},
      "foreignKeys": {},
      "compositePrimaryKeys": {},
      "uniqueConstraints": {
        "users_email_unique": {
          "name": "users_email_unique",
          "nullsNotDistinct": false,
          "columns": [
            "email"
          ]
        }
      },
      "policies": {},
      "checkConstraints": {},
      "isRLSEnabled": false
    },
    "public.volumes_snapshots": {
      "name": "volumes_snapshots",
      "schema": "",
      "columns": {
        "id": {
          "name": "id",
          "type": "bigint",
          "primaryKey": false,
          "notNull": true,
          "identity": {
            "type": "always",
            "name": "volumes_snapshots_id_seq",
            "schema": "public",
            "increment": "1",
            "startWith": "1",
            "minValue": "1",
            "maxValue": "9223372036854775807",
            "cache": "1",
            "cycle": false
          }
        },
        "taken_at": {
          "name": "taken_at",
          "type": "timestamp with time zone",
          "primaryKey": false,
          "notNull": true
        },
        "event_id": {
          "name": "event_id",
          "type": "integer",
          "primaryKey": false,
          "notNull": true
        },
        "market_id": {
          "name": "market_id",
          "type": "integer",
          "primaryKey": false,
          "notNull": true
        },
        "selection_id": {
          "name": "selection_id",
          "type": "integer",
          "primaryKey": false,
          "notNull": true
        },
        "book_id": {
          "name": "book_id",
          "type": "integer",
          "primaryKey": false,
          "notNull": true
        },
        "matched_volume": {
          "name": "matched_volume",
          "type": "double precision",
          "primaryKey": false,
          "notNull": false
        },
        "back_best": {
          "name": "back_best",
          "type": "double precision",
          "primaryKey": false,
          "notNull": false
        },
        "lay_best": {
          "name": "lay_best",
          "type": "double precision",
          "primaryKey": false,
          "notNull": false
        }
      },
      "indexes": {
        "idx_volumes_lookup": {
          "name": "idx_volumes_lookup",
          "columns": [
            {
              "expression": "event_id",
              "isExpression": false,
              "asc": true,
              "nulls": "last"
            },
            {
              "expression": "market_id",
              "isExpression": false,
              "asc": true,
              "nulls": "last"
            },
            {
              "expression": "selection_id",
              "isExpression": false,
              "asc": true,
              "nulls": "last"
            },
            {
              "expression": "book_id",
              "isExpression": false,
              "asc": true,
              "nulls": "last"
            },
            {
              "expression": "taken_at",
              "isExpression": false,
              "asc": true,
              "nulls": "last"
            }
          ],
          "isUnique": false,
          "concurrently": false,
          "method": "btree",
          "with": {}
        }
      },
      "foreignKeys": {
        "volumes_snapshots_event_id_events_id_fk": {
          "name": "volumes_snapshots_event_id_events_id_fk",
          "tableFrom": "volumes_snapshots",
          "tableTo": "events",
          "columnsFrom": [
            "event_id"
          ],
          "columnsTo": [
            "id"
          ],
          "onDelete": "cascade",
          "onUpdate": "no action"
        },
        "volumes_snapshots_market_id_markets_id_fk": {
          "name": "volumes_snapshots_market_id_markets_id_fk",
          "tableFrom": "volumes_snapshots",
          "tableTo": "markets",
          "columnsFrom": [
            "market_id"
          ],
          "columnsTo": [
            "id"
          ],
          "onDelete": "no action",
          "onUpdate": "no action"
        },
        "volumes_snapshots_selection_id_selections_id_fk": {
          "name": "volumes_snapshots_selection_id_selections_id_fk",
          "tableFrom": "volumes_snapshots",
          "tableTo": "selections",
          "columnsFrom": [
            "selection_id"
          ],
          "columnsTo": [
            "id"
          ],
          "onDelete": "no action",
          "onUpdate": "no action"
        },
        "volumes_snapshots_book_id_books_id_fk": {
          "name": "volumes_snapshots_book_id_books_id_fk",
          "tableFrom": "volumes_snapshots",
          "tableTo": "books",
          "columnsFrom": [
            "book_id"
          ],
          "columnsTo": [
            "id"
          ],
          "onDelete": "no action",
          "onUpdate": "no action"
        }
      },
      "compositePrimaryKeys": {
        "volumes_snapshots_id_taken_at_pk": {
          "name": "volumes_snapshots_id_taken_at_pk",
          "columns": [
            "id",
            "taken_at"
          ]
        }
      },
      "uniqueConstraints": {},
      "policies": {},
      "checkConstraints": {},
      "isRLSEnabled": false
    }
  },
  "enums": {
    "public.event_status": {
      "name": "event_status",
      "schema": "public",
      "values": [
        "scheduled",
        "in_play",
        "finished",
        "postponed",
        "cancelled"
      ]
    },
    "public.ingestion_status": {
      "name": "ingestion_status",
      "schema": "public",
      "values": [
        "running",
        "success",
        "partial",
        "failed"
      ]
    },
    "public.mapping_status": {
      "name": "mapping_status",
      "schema": "public",
      "values": [
        "pending",
        "resolved",
        "rejected"
      ]
    },
    "public.signal_status": {
      "name": "signal_status",
      "schema": "public",
      "values": [
        "active",
        "expired",
        "consumed"
      ]
    },
    "public.signal_type": {
      "name": "signal_type",
      "schema": "public",
      "values": [
        "arb",
        "value",
        "steam"
      ]
    },
    "public.source_tier": {
      "name": "source_tier",
      "schema": "public",
      "values": [
        "easy",
        "medium",
        "hard"
      ]
    },
    "public.user_role": {
      "name": "user_role",
      "schema": "public",
      "values": [
        "admin",
        "viewer"
      ]
    }
  },
  "schemas": {},
  "sequences": {},
  "roles": {},
  "policies": {},
  "views": {},
  "_meta": {
    "columns": {},
    "schemas": {},
    "tables": {}
  }
}